{
    "pdf_info": [
        {
            "para_blocks": [
                {
                    "bbox": [
                        86,
                        232,
                        510,
                        323
                    ],
                    "type": "title",
                    "angle": 0,
                    "lines": [
                        {
                            "bbox": [
                                86,
                                232,
                                510,
                                323
                            ],
                            "spans": [
                                {
                                    "bbox": [
                                        86,
                                        232,
                                        510,
                                        323
                                    ],
                                    "type": "text",
                                    "content": "新品零部件需求BOM变更操作指导书"
                                }
                            ]
                        }
                    ],
                    "index": 1
                },
                {
                    "bbox": [
                        271,
                        373,
                        322,
                        392
                    ],
                    "type": "text",
                    "angle": 0,
                    "lines": [
                        {
                            "bbox": [
                                271,
                                373,
                                322,
                                392
                            ],
                            "spans": [
                                {
                                    "bbox": [
                                        271,
                                        373,
                                        322,
                                        392
                                    ],
                                    "type": "text",
                                    "content": "共7页"
                                }
                            ]
                        }
                    ],
                    "index": 2
                },
                {
                    "bbox": [
                        183,
                        649,
                        410,
                        666
                    ],
                    "type": "text",
                    "angle": 0,
                    "lines": [
                        {
                            "bbox": [
                                183,
                                649,
                                410,
                                666
                            ],
                            "spans": [
                                {
                                    "bbox": [
                                        183,
                                        649,
                                        410,
                                        666
                                    ],
                                    "type": "text",
                                    "content": "陕西千山航空电子有限责任公司"
                                }
                            ]
                        }
                    ],
                    "index": 3
                },
                {
                    "bbox": [
                        254,
                        693,
                        337,
                        711
                    ],
                    "type": "text",
                    "angle": 0,
                    "lines": [
                        {
                            "bbox": [
                                254,
                                693,
                                337,
                                711
                            ],
                            "spans": [
                                {
                                    "bbox": [
                                        254,
                                        693,
                                        337,
                                        711
                                    ],
                                    "type": "text",
                                    "content": "2025年9月"
                                }
                            ]
                        }
                    ],
                    "index": 4
                }
            ],
            "discarded_blocks": [
                {
                    "bbox": [
                        68,
                        84,
                        101,
                        101
                    ],
                    "type": "header",
                    "angle": 0,
                    "lines": [
                        {
                            "bbox": [
                                68,
                                84,
                                101,
                                101
                            ],
                            "spans": [
                                {
                                    "bbox": [
                                        68,
                                        84,
                                        101,
                                        101
                                    ],
                                    "type": "text",
                                    "content": "受控"
                                }
                            ]
                        }
                    ],
                    "index": 0
                }
            ],
            "page_size": [
                595,
                841
            ],
            "page_idx": 0
        },
        {
            "para_blocks": [
                {
                    "bbox": [
                        277,
                        80,
                        318,
                        100
                    ],
                    "type": "title",
                    "angle": 0,
                    "lines": [
                        {
                            "bbox": [
                                277,
                                80,
                                318,
                                100
                            ],
                            "spans": [
                                {
                                    "bbox": [
                                        277,
                                        80,
                                        318,
                                        100
                                    ],
                                    "type": "text",
                                    "content": "目次"
                                }
                            ]
                        }
                    ],
                    "index": 0
                },
                {
                    "bbox": [
                        83,
                        126,
                        504,
                        162
                    ],
                    "type": "list",
                    "angle": 0,
                    "index": 3,
                    "blocks": [
                        {
                            "bbox": [
                                83,
                                126,
                                504,
                                142
                            ],
                            "type": "text",
                            "angle": 0,
                            "lines": [
                                {
                                    "bbox": [
                                        83,
                                        126,
                                        504,
                                        142
                                    ],
                                    "spans": [
                                        {
                                            "bbox": [
                                                83,
                                                126,
                                                504,
                                                142
                                            ],
                                            "type": "text",
                                            "content": "1适用范围"
                                        }
                                    ]
                                }
                            ],
                            "index": 1
                        },
                        {
                            "bbox": [
                                84,
                                148,
                                503,
                                162
                            ],
                            "type": "text",
                            "angle": 0,
                            "lines": [
                                {
                                    "bbox": [
                                        84,
                                        148,
                                        503,
                                        162
                                    ],
                                    "spans": [
                                        {
                                            "bbox": [
                                                84,
                                                148,
                                                503,
                                                162
                                            ],
                                            "type": "text",
                                            "content": "2 操作向导"
                                        }
                                    ]
                                }
                            ],
                            "index": 2
                        }
                    ],
                    "sub_type": "text"
                },
                {
                    "bbox": [
                        83,
                        168,
                        504,
                        184
                    ],
                    "type": "text",
                    "angle": 0,
                    "lines": [
                        {
                            "bbox": [
                                83,
                                168,
                                504,
                                184
                            ],
                            "spans": [
                                {
                                    "bbox": [
                                        83,
                                        168,
                                        504,
                                        184
                                    ],
                                    "type": "text",
                                    "content": "2.1 释放多余物资需求（视情） 1"
                                }
                            ]
                        }
                    ],
                    "index": 4
                },
                {
                    "bbox": [
                        84,
                        190,
                        504,
                        225
                    ],
                    "type": "list",
                    "angle": 0,
                    "index": 7,
                    "blocks": [
                        {
                            "bbox": [
                                84,
                                190,
                                504,
                                205
                            ],
                            "type": "text",
                            "angle": 0,
                            "lines": [
                                {
                                    "bbox": [
                                        84,
                                        190,
                                        504,
                                        205
                                    ],
                                    "spans": [
                                        {
                                            "bbox": [
                                                84,
                                                190,
                                                504,
                                                205
                                            ],
                                            "type": "text",
                                            "content": "2.2物资补充投入（视情） 2"
                                        }
                                    ]
                                }
                            ],
                            "index": 5
                        },
                        {
                            "bbox": [
                                84,
                                211,
                                504,
                                225
                            ],
                            "type": "text",
                            "angle": 0,
                            "lines": [
                                {
                                    "bbox": [
                                        84,
                                        211,
                                        504,
                                        225
                                    ],
                                    "spans": [
                                        {
                                            "bbox": [
                                                84,
                                                211,
                                                504,
                                                225
                                            ],
                                            "type": "text",
                                            "content": "2.3 重新勾选BOM，更新配套单"
                                        }
                                    ]
                                }
                            ],
                            "index": 6
                        }
                    ],
                    "sub_type": "text"
                }
            ],
            "discarded_blocks": [
                {
                    "bbox": [
                        196,
                        790,
                        360,
                        802
                    ],
                    "type": "footer",
                    "angle": 0,
                    "lines": [
                        {
                            "bbox": [
                                196,
                                790,
                                360,
                                802
                            ],
                            "spans": [
                                {
                                    "bbox": [
                                        196,
                                        790,
                                        360,
                                        802
                                    ],
                                    "type": "text",
                                    "content": "陕西千山航空电子有限责任公司版权所有"
                                }
                            ]
                        }
                    ],
                    "index": 8
                },
                {
                    "bbox": [
                        504,
                        788,
                        511,
                        798
                    ],
                    "type": "page_number",
                    "angle": 0,
                    "lines": [
                        {
                            "bbox": [
                                504,
                                788,
                                511,
                                798
                            ],
                            "spans": [
                                {
                                    "bbox": [
                                        504,
                                        788,
                                        511,
                                        798
                                    ],
                                    "type": "text",
                                    "content": "I"
                                }
                            ]
                        }
                    ],
                    "index": 9
                }
            ],
            "page_size": [
                595,
                841
            ],
            "page_idx": 1
        },
        {
            "para_blocks": [
                {
                    "bbox": [
                        83,
                        76,
                        153,
                        90
                    ],
                    "type": "title",
                    "angle": 0,
                    "lines": [
                        {
                            "bbox": [
                                83,
                                76,
                                153,
                                90
                            ],
                            "spans": [
                                {
                                    "bbox": [
                                        83,
                                        76,
                                        153,
                                        90
                                    ],
                                    "type": "text",
                                    "content": "1 适用范围"
                                }
                            ]
                        }
                    ],
                    "index": 0
                },
                {
                    "bbox": [
                        81,
                        103,
                        505,
                        160
                    ],
                    "type": "text",
                    "angle": 0,
                    "lines": [
                        {
                            "bbox": [
                                81,
                                103,
                                505,
                                160
                            ],
                            "spans": [
                                {
                                    "bbox": [
                                        81,
                                        103,
                                        505,
                                        160
                                    ],
                                    "type": "text",
                                    "content": "本文件适用于新品科研样机按照勾选BOM的方式投入后，发生的设计更改、投入物资变化后，更新前期已勾选的BOM，达到“按需投入、按需产出”目的，使得配套单精准、物料上线精准、产出过程顺利。"
                                }
                            ]
                        }
                    ],
                    "index": 1
                },
                {
                    "bbox": [
                        82,
                        172,
                        152,
                        186
                    ],
                    "type": "title",
                    "angle": 0,
                    "lines": [
                        {
                            "bbox": [
                                82,
                                172,
                                152,
                                186
                            ],
                            "spans": [
                                {
                                    "bbox": [
                                        82,
                                        172,
                                        152,
                                        186
                                    ],
                                    "type": "text",
                                    "content": "2 操作向导"
                                }
                            ]
                        }
                    ],
                    "index": 2
                },
                {
                    "bbox": [
                        81,
                        198,
                        504,
                        234
                    ],
                    "type": "text",
                    "angle": 0,
                    "lines": [
                        {
                            "bbox": [
                                81,
                                198,
                                504,
                                234
                            ],
                            "spans": [
                                {
                                    "bbox": [
                                        81,
                                        198,
                                        504,
                                        234
                                    ],
                                    "type": "text",
                                    "content": "当发生的设计更改、投入物资变化后，为更新配套单，需更新前期已在零部件需求申请中勾选的BOM。分三个步骤，具体如下。"
                                }
                            ]
                        }
                    ],
                    "index": 3
                },
                {
                    "bbox": [
                        82,
                        241,
                        251,
                        255
                    ],
                    "type": "title",
                    "angle": 0,
                    "lines": [
                        {
                            "bbox": [
                                82,
                                241,
                                251,
                                255
                            ],
                            "spans": [
                                {
                                    "bbox": [
                                        82,
                                        241,
                                        251,
                                        255
                                    ],
                                    "type": "text",
                                    "content": "2.1 释放多余物资需求（视情）"
                                }
                            ]
                        }
                    ],
                    "index": 4
                },
                {
                    "bbox": [
                        81,
                        261,
                        504,
                        298
                    ],
                    "type": "text",
                    "angle": 0,
                    "lines": [
                        {
                            "bbox": [
                                81,
                                261,
                                504,
                                298
                            ],
                            "spans": [
                                {
                                    "bbox": [
                                        81,
                                        261,
                                        504,
                                        298
                                    ],
                                    "type": "text",
                                    "content": "当设计更改、产出策略及目标发生变化后，存在前期物资多余的情况，需对前期已投入物资进行需求变更，释放需求资源。"
                                }
                            ]
                        }
                    ],
                    "index": 5
                },
                {
                    "bbox": [
                        105,
                        303,
                        470,
                        318
                    ],
                    "type": "text",
                    "angle": 0,
                    "lines": [
                        {
                            "bbox": [
                                105,
                                303,
                                470,
                                318
                            ],
                            "spans": [
                                {
                                    "bbox": [
                                        105,
                                        303,
                                        470,
                                        318
                                    ],
                                    "type": "text",
                                    "content": "步骤1：点击中航工业千山门户系统首页如图所示标注进入，见下图。"
                                }
                            ]
                        }
                    ],
                    "index": 6
                },
                {
                    "type": "image",
                    "bbox": [
                        82,
                        318,
                        508,
                        448
                    ],
                    "blocks": [
                        {
                            "bbox": [
                                82,
                                318,
                                508,
                                448
                            ],
                            "lines": [
                                {
                                    "bbox": [
                                        82,
                                        318,
                                        508,
                                        448
                                    ],
                                    "spans": [
                                        {
                                            "bbox": [
                                                82,
                                                318,
                                                508,
                                                448
                                            ],
                                            "type": "image",
                                            "image_path": "4eb7381c66b24b0892c9d807bc5215be20e7c6c08931a67bd2c311790c5d0662.jpg"
                                        }
                                    ]
                                }
                            ],
                            "index": 7,
                            "angle": 0,
                            "type": "image_body"
                        }
                    ],
                    "index": 7
                },
                {
                    "bbox": [
                        106,
                        458,
                        374,
                        472
                    ],
                    "type": "text",
                    "angle": 0,
                    "lines": [
                        {
                            "bbox": [
                                106,
                                458,
                                374,
                                472
                            ],
                            "spans": [
                                {
                                    "bbox": [
                                        106,
                                        458,
                                        374,
                                        472
                                    ],
                                    "type": "text",
                                    "content": "步骤2：生产计划管控系统进入后默认页面见下图。"
                                }
                            ]
                        }
                    ],
                    "index": 8
                },
                {
                    "type": "image",
                    "bbox": [
                        83,
                        478,
                        511,
                        642
                    ],
                    "blocks": [
                        {
                            "bbox": [
                                83,
                                478,
                                511,
                                642
                            ],
                            "lines": [
                                {
                                    "bbox": [
                                        83,
                                        478,
                                        511,
                                        642
                                    ],
                                    "spans": [
                                        {
                                            "bbox": [
                                                83,
                                                478,
                                                511,
                                                642
                                            ],
                                            "type": "image",
                                            "image_path": "399750a8df568b14ae6cc04c5a5bef9fed2621394f1efbb6d0afc81350f75f24.jpg"
                                        }
                                    ]
                                }
                            ],
                            "index": 9,
                            "angle": 0,
                            "type": "image_body"
                        }
                    ],
                    "index": 9
                },
                {
                    "bbox": [
                        81,
                        653,
                        510,
                        689
                    ],
                    "type": "text",
                    "angle": 0,
                    "lines": [
                        {
                            "bbox": [
                                81,
                                653,
                                510,
                                689
                            ],
                            "spans": [
                                {
                                    "bbox": [
                                        81,
                                        653,
                                        510,
                                        689
                                    ],
                                    "type": "text",
                                    "content": "步骤3：选择“生产计划管理”——“零星需求管理”——“零星需求变更申请”。"
                                }
                            ]
                        }
                    ],
                    "index": 10
                }
            ],
            "discarded_blocks": [
                {
                    "bbox": [
                        217,
                        796,
                        381,
                        807
                    ],
                    "type": "footer",
                    "angle": 0,
                    "lines": [
                        {
                            "bbox": [
                                217,
                                796,
                                381,
                                807
                            ],
                            "spans": [
                                {
                                    "bbox": [
                                        217,
                                        796,
                                        381,
                                        807
                                    ],
                                    "type": "text",
                                    "content": "陕西千山航空电子有限责任公司版权所有"
                                }
                            ]
                        }
                    ],
                    "index": 11
                },
                {
                    "bbox": [
                        447,
                        794,
                        510,
                        806
                    ],
                    "type": "page_number",
                    "angle": 0,
                    "lines": [
                        {
                            "bbox": [
                                447,
                                794,
                                510,
                                806
                            ],
                            "spans": [
                                {
                                    "bbox": [
                                        447,
                                        794,
                                        510,
                                        806
                                    ],
                                    "type": "text",
                                    "content": "共5页 第1页"
                                }
                            ]
                        }
                    ],
                    "index": 12
                }
            ],
            "page_size": [
                595,
                841
            ],
            "page_idx": 2
        },
        {
            "para_blocks": [
                {
                    "type": "image",
                    "bbox": [
                        83,
                        67,
                        510,
                        202
                    ],
                    "blocks": [
                        {
                            "bbox": [
                                83,
                                67,
                                510,
                                202
                            ],
                            "lines": [
                                {
                                    "bbox": [
                                        83,
                                        67,
                                        510,
                                        202
                                    ],
                                    "spans": [
                                        {
                                            "bbox": [
                                                83,
                                                67,
                                                510,
                                                202
                                            ],
                                            "type": "image",
                                            "image_path": "1effc6456f82dc43b9be5af6db0d9990eccc6e4046b2b1e4f7c73ffd7090b3a6.jpg"
                                        }
                                    ]
                                }
                            ],
                            "index": 0,
                            "angle": 0,
                            "type": "image_body"
                        }
                    ],
                    "index": 0
                },
                {
                    "bbox": [
                        81,
                        210,
                        511,
                        267
                    ],
                    "type": "text",
                    "angle": 0,
                    "lines": [
                        {
                            "bbox": [
                                81,
                                210,
                                511,
                                267
                            ],
                            "spans": [
                                {
                                    "bbox": [
                                        81,
                                        210,
                                        511,
                                        267
                                    ],
                                    "type": "text",
                                    "content": "步骤4：点击“添加”，通过项目代号、物料编码、器件牌号、图号等查询信息，找到需求变更的物料信息，变更需求数量，提交审批，审批通过后，即可完成物资需求变更及资源释放。"
                                }
                            ]
                        }
                    ],
                    "index": 1
                },
                {
                    "type": "image",
                    "bbox": [
                        83,
                        272,
                        511,
                        370
                    ],
                    "blocks": [
                        {
                            "bbox": [
                                83,
                                272,
                                511,
                                370
                            ],
                            "lines": [
                                {
                                    "bbox": [
                                        83,
                                        272,
                                        511,
                                        370
                                    ],
                                    "spans": [
                                        {
                                            "bbox": [
                                                83,
                                                272,
                                                511,
                                                370
                                            ],
                                            "type": "image",
                                            "image_path": "af4730bf6da624153afcff77ed18f39244e977e135771c18efad684a81e96809.jpg"
                                        }
                                    ]
                                }
                            ],
                            "index": 2,
                            "angle": 0,
                            "type": "image_body"
                        }
                    ],
                    "index": 2
                },
                {
                    "type": "image",
                    "bbox": [
                        83,
                        371,
                        511,
                        592
                    ],
                    "blocks": [
                        {
                            "bbox": [
                                83,
                                371,
                                511,
                                592
                            ],
                            "lines": [
                                {
                                    "bbox": [
                                        83,
                                        371,
                                        511,
                                        592
                                    ],
                                    "spans": [
                                        {
                                            "bbox": [
                                                83,
                                                371,
                                                511,
                                                592
                                            ],
                                            "type": "image",
                                            "image_path": "6f48b9127cd988a83294f5518fc8b952ffb41e14e1b13dd9ad2b020e5759c92e.jpg"
                                        }
                                    ]
                                }
                            ],
                            "index": 3,
                            "angle": 0,
                            "type": "image_body"
                        }
                    ],
                    "index": 3
                },
                {
                    "bbox": [
                        82,
                        601,
                        227,
                        616
                    ],
                    "type": "title",
                    "angle": 0,
                    "lines": [
                        {
                            "bbox": [
                                82,
                                601,
                                227,
                                616
                            ],
                            "spans": [
                                {
                                    "bbox": [
                                        82,
                                        601,
                                        227,
                                        616
                                    ],
                                    "type": "text",
                                    "content": "2.2 物资补充投入（视情）"
                                }
                            ]
                        }
                    ],
                    "index": 4
                },
                {
                    "bbox": [
                        81,
                        622,
                        507,
                        680
                    ],
                    "type": "text",
                    "angle": 0,
                    "lines": [
                        {
                            "bbox": [
                                81,
                                622,
                                507,
                                680
                            ],
                            "spans": [
                                {
                                    "bbox": [
                                        81,
                                        622,
                                        507,
                                        680
                                    ],
                                    "type": "text",
                                    "content": "当设计更改、产出策略及目标发生变化后，前期投入物资发生变化，新增的物资未投入时，则可通过“新品零部件需求申请（新）”完成补充投入，或通过“零星需求申请”完成补充投入。"
                                }
                            ]
                        }
                    ],
                    "index": 5
                },
                {
                    "bbox": [
                        81,
                        685,
                        502,
                        722
                    ],
                    "type": "text",
                    "angle": 0,
                    "lines": [
                        {
                            "bbox": [
                                81,
                                685,
                                502,
                                722
                            ],
                            "spans": [
                                {
                                    "bbox": [
                                        81,
                                        685,
                                        502,
                                        722
                                    ],
                                    "type": "text",
                                    "content": "若设计更改的内容为调整装配关系，联动导致BOM结构变化，物资无实质性变化是，重新勾选BOM不涉及物资变化，无需进行物资补充投入。"
                                }
                            ]
                        }
                    ],
                    "index": 6
                },
                {
                    "bbox": [
                        82,
                        727,
                        265,
                        742
                    ],
                    "type": "title",
                    "angle": 0,
                    "lines": [
                        {
                            "bbox": [
                                82,
                                727,
                                265,
                                742
                            ],
                            "spans": [
                                {
                                    "bbox": [
                                        82,
                                        727,
                                        265,
                                        742
                                    ],
                                    "type": "text",
                                    "content": "2.3 重新勾选BOM，更新配套单"
                                }
                            ]
                        }
                    ],
                    "index": 7
                },
                {
                    "bbox": [
                        105,
                        754,
                        509,
                        769
                    ],
                    "type": "text",
                    "angle": 0,
                    "lines": [
                        {
                            "bbox": [
                                105,
                                754,
                                509,
                                769
                            ],
                            "spans": [
                                {
                                    "bbox": [
                                        105,
                                        754,
                                        509,
                                        769
                                    ],
                                    "type": "text",
                                    "content": "步骤5：选择“生产计划管理”——“新品计划管理”——“新品零部件管"
                                }
                            ]
                        }
                    ],
                    "index": 8
                }
            ],
            "discarded_blocks": [
                {
                    "bbox": [
                        217,
                        796,
                        381,
                        808
                    ],
                    "type": "footer",
                    "angle": 0,
                    "lines": [
                        {
                            "bbox": [
                                217,
                                796,
                                381,
                                808
                            ],
                            "spans": [
                                {
                                    "bbox": [
                                        217,
                                        796,
                                        381,
                                        808
                                    ],
                                    "type": "text",
                                    "content": "陕西千山航空电子有限责任公司版权所有"
                                }
                            ]
                        }
                    ],
                    "index": 9
                },
                {
                    "bbox": [
                        447,
                        794,
                        510,
                        806
                    ],
                    "type": "page_number",
                    "angle": 0,
                    "lines": [
                        {
                            "bbox": [
                                447,
                                794,
                                510,
                                806
                            ],
                            "spans": [
                                {
                                    "bbox": [
                                        447,
                                        794,
                                        510,
                                        806
                                    ],
                                    "type": "text",
                                    "content": "共5页 第2页"
                                }
                            ]
                        }
                    ],
                    "index": 10
                }
            ],
            "page_size": [
                595,
                841
            ],
            "page_idx": 3
        },
        {
            "para_blocks": [
                {
                    "bbox": [
                        82,
                        75,
                        339,
                        91
                    ],
                    "type": "text",
                    "angle": 0,
                    "lines": [
                        {
                            "bbox": [
                                82,
                                75,
                                339,
                                91
                            ],
                            "spans": [
                                {
                                    "bbox": [
                                        82,
                                        75,
                                        339,
                                        91
                                    ],
                                    "type": "text",
                                    "content": "理（新）”——“新品零部件需求BOM变更”。"
                                }
                            ]
                        }
                    ],
                    "index": 0
                },
                {
                    "type": "image",
                    "bbox": [
                        83,
                        95,
                        516,
                        226
                    ],
                    "blocks": [
                        {
                            "bbox": [
                                83,
                                95,
                                516,
                                226
                            ],
                            "lines": [
                                {
                                    "bbox": [
                                        83,
                                        95,
                                        516,
                                        226
                                    ],
                                    "spans": [
                                        {
                                            "bbox": [
                                                83,
                                                95,
                                                516,
                                                226
                                            ],
                                            "type": "image",
                                            "image_path": "c2a811d20776dd2a9cc809b047179db142613e9f7cd2c72835721d9283768419.jpg"
                                        }
                                    ]
                                }
                            ],
                            "index": 1,
                            "angle": 0,
                            "type": "image_body"
                        }
                    ],
                    "index": 1
                },
                {
                    "bbox": [
                        107,
                        235,
                        231,
                        250
                    ],
                    "type": "text",
                    "angle": 0,
                    "lines": [
                        {
                            "bbox": [
                                107,
                                235,
                                231,
                                250
                            ],
                            "spans": [
                                {
                                    "bbox": [
                                        107,
                                        235,
                                        231,
                                        250
                                    ],
                                    "type": "text",
                                    "content": "步骤6：点击“添加”。"
                                }
                            ]
                        }
                    ],
                    "index": 2
                },
                {
                    "type": "image",
                    "bbox": [
                        83,
                        255,
                        514,
                        388
                    ],
                    "blocks": [
                        {
                            "bbox": [
                                83,
                                255,
                                514,
                                388
                            ],
                            "lines": [
                                {
                                    "bbox": [
                                        83,
                                        255,
                                        514,
                                        388
                                    ],
                                    "spans": [
                                        {
                                            "bbox": [
                                                83,
                                                255,
                                                514,
                                                388
                                            ],
                                            "type": "image",
                                            "image_path": "3ba32a62e088bf3ba30c2a4c8aa6fae074b75e4cb33cc0f935270cc43e1c42a3.jpg"
                                        }
                                    ]
                                }
                            ],
                            "index": 3,
                            "angle": 0,
                            "type": "image_body"
                        }
                    ],
                    "index": 3
                },
                {
                    "bbox": [
                        106,
                        397,
                        446,
                        412
                    ],
                    "type": "text",
                    "angle": 0,
                    "lines": [
                        {
                            "bbox": [
                                106,
                                397,
                                446,
                                412
                            ],
                            "spans": [
                                {
                                    "bbox": [
                                        106,
                                        397,
                                        446,
                                        412
                                    ],
                                    "type": "text",
                                    "content": "步骤7：选择前期已执行的新品零部件需求，点击“确认选择”。"
                                }
                            ]
                        }
                    ],
                    "index": 4
                },
                {
                    "type": "image",
                    "bbox": [
                        83,
                        417,
                        512,
                        711
                    ],
                    "blocks": [
                        {
                            "bbox": [
                                83,
                                417,
                                512,
                                711
                            ],
                            "lines": [
                                {
                                    "bbox": [
                                        83,
                                        417,
                                        512,
                                        711
                                    ],
                                    "spans": [
                                        {
                                            "bbox": [
                                                83,
                                                417,
                                                512,
                                                711
                                            ],
                                            "type": "image",
                                            "image_path": "3f18369356ea77f056cb14dbd40b153ff741b5ae2a92803d65a383958da1c61a.jpg"
                                        }
                                    ]
                                }
                            ],
                            "index": 5,
                            "angle": 0,
                            "type": "image_body"
                        }
                    ],
                    "index": 5
                },
                {
                    "bbox": [
                        106,
                        722,
                        514,
                        737
                    ],
                    "type": "text",
                    "angle": 0,
                    "lines": [
                        {
                            "bbox": [
                                106,
                                722,
                                514,
                                737
                            ],
                            "spans": [
                                {
                                    "bbox": [
                                        106,
                                        722,
                                        514,
                                        737
                                    ],
                                    "type": "text",
                                    "content": "步骤8：在“BOM选择”处，点击“BOM选择”，重新进行BOM勾选确认。"
                                }
                            ]
                        }
                    ],
                    "index": 6
                }
            ],
            "discarded_blocks": [
                {
                    "bbox": [
                        217,
                        796,
                        381,
                        808
                    ],
                    "type": "footer",
                    "angle": 0,
                    "lines": [
                        {
                            "bbox": [
                                217,
                                796,
                                381,
                                808
                            ],
                            "spans": [
                                {
                                    "bbox": [
                                        217,
                                        796,
                                        381,
                                        808
                                    ],
                                    "type": "text",
                                    "content": "陕西千山航空电子有限责任公司版权所有"
                                }
                            ]
                        }
                    ],
                    "index": 7
                },
                {
                    "bbox": [
                        447,
                        794,
                        511,
                        806
                    ],
                    "type": "page_number",
                    "angle": 0,
                    "lines": [
                        {
                            "bbox": [
                                447,
                                794,
                                511,
                                806
                            ],
                            "spans": [
                                {
                                    "bbox": [
                                        447,
                                        794,
                                        511,
                                        806
                                    ],
                                    "type": "text",
                                    "content": "共5页 第3页"
                                }
                            ]
                        }
                    ],
                    "index": 8
                }
            ],
            "page_size": [
                595,
                841
            ],
            "page_idx": 4
        },
        {
            "para_blocks": [
                {
                    "type": "image",
                    "bbox": [
                        83,
                        67,
                        511,
                        241
                    ],
                    "blocks": [
                        {
                            "bbox": [
                                83,
                                67,
                                511,
                                241
                            ],
                            "lines": [
                                {
                                    "bbox": [
                                        83,
                                        67,
                                        511,
                                        241
                                    ],
                                    "spans": [
                                        {
                                            "bbox": [
                                                83,
                                                67,
                                                511,
                                                241
                                            ],
                                            "type": "image",
                                            "image_path": "0a6146f1be1d28d4d47a8ac7593e2ca6876d6661335ceb4bc8554ce02fcfbe53.jpg"
                                        }
                                    ]
                                }
                            ],
                            "index": 0,
                            "angle": 0,
                            "type": "image_body"
                        }
                    ],
                    "index": 0
                },
                {
                    "bbox": [
                        82,
                        250,
                        509,
                        285
                    ],
                    "type": "text",
                    "angle": 0,
                    "lines": [
                        {
                            "bbox": [
                                82,
                                250,
                                509,
                                285
                            ],
                            "spans": [
                                {
                                    "bbox": [
                                        82,
                                        250,
                                        509,
                                        285
                                    ],
                                    "type": "text",
                                    "content": "步骤9：在BOM待选择区域，选择确认新的BOM，点击“确认选择”，点击“☑”。"
                                }
                            ]
                        }
                    ],
                    "index": 1
                },
                {
                    "type": "image",
                    "bbox": [
                        83,
                        291,
                        508,
                        467
                    ],
                    "blocks": [
                        {
                            "bbox": [
                                83,
                                291,
                                508,
                                467
                            ],
                            "lines": [
                                {
                                    "bbox": [
                                        83,
                                        291,
                                        508,
                                        467
                                    ],
                                    "spans": [
                                        {
                                            "bbox": [
                                                83,
                                                291,
                                                508,
                                                467
                                            ],
                                            "type": "image",
                                            "image_path": "d4b28c7aa0f34ede37329c97d790460c896dc9b1b2398f12220d2d2fd161c398.jpg"
                                        }
                                    ]
                                }
                            ],
                            "index": 2,
                            "angle": 0,
                            "type": "image_body"
                        }
                    ],
                    "index": 2
                },
                {
                    "type": "image",
                    "bbox": [
                        83,
                        470,
                        510,
                        687
                    ],
                    "blocks": [
                        {
                            "bbox": [
                                83,
                                470,
                                510,
                                687
                            ],
                            "lines": [
                                {
                                    "bbox": [
                                        83,
                                        470,
                                        510,
                                        687
                                    ],
                                    "spans": [
                                        {
                                            "bbox": [
                                                83,
                                                470,
                                                510,
                                                687
                                            ],
                                            "type": "image",
                                            "image_path": "3349fa3900e89157fd76812a3d316219532d6ad280693ca645c174014fe8e25c.jpg"
                                        }
                                    ]
                                }
                            ],
                            "index": 3,
                            "angle": 0,
                            "type": "image_body"
                        }
                    ],
                    "index": 3
                }
            ],
            "discarded_blocks": [
                {
                    "bbox": [
                        217,
                        796,
                        381,
                        807
                    ],
                    "type": "footer",
                    "angle": 0,
                    "lines": [
                        {
                            "bbox": [
                                217,
                                796,
                                381,
                                807
                            ],
                            "spans": [
                                {
                                    "bbox": [
                                        217,
                                        796,
                                        381,
                                        807
                                    ],
                                    "type": "text",
                                    "content": "陕西千山航空电子有限责任公司版权所有"
                                }
                            ]
                        }
                    ],
                    "index": 4
                },
                {
                    "bbox": [
                        447,
                        794,
                        510,
                        805
                    ],
                    "type": "page_number",
                    "angle": 0,
                    "lines": [
                        {
                            "bbox": [
                                447,
                                794,
                                510,
                                805
                            ],
                            "spans": [
                                {
                                    "bbox": [
                                        447,
                                        794,
                                        510,
                                        805
                                    ],
                                    "type": "text",
                                    "content": "共5页 第4页"
                                }
                            ]
                        }
                    ],
                    "index": 5
                }
            ],
            "page_size": [
                595,
                841
            ],
            "page_idx": 5
        },
        {
            "para_blocks": [
                {
                    "type": "image",
                    "bbox": [
                        83,
                        67,
                        511,
                        245
                    ],
                    "blocks": [
                        {
                            "bbox": [
                                83,
                                67,
                                511,
                                245
                            ],
                            "lines": [
                                {
                                    "bbox": [
                                        83,
                                        67,
                                        511,
                                        245
                                    ],
                                    "spans": [
                                        {
                                            "bbox": [
                                                83,
                                                67,
                                                511,
                                                245
                                            ],
                                            "type": "image",
                                            "image_path": "476a9bc6e239462faa1998e02cfcf2907ad63968d72d33bfa5ca655720a9d01d.jpg"
                                        }
                                    ]
                                }
                            ],
                            "index": 0,
                            "angle": 0,
                            "type": "image_body"
                        }
                    ],
                    "index": 0
                },
                {
                    "bbox": [
                        81,
                        254,
                        511,
                        290
                    ],
                    "type": "text",
                    "angle": 0,
                    "lines": [
                        {
                            "bbox": [
                                81,
                                254,
                                511,
                                290
                            ],
                            "spans": [
                                {
                                    "bbox": [
                                        81,
                                        254,
                                        511,
                                        290
                                    ],
                                    "type": "text",
                                    "content": "步骤10：提交审批，分别通过部门领导、副总师审批节点审批，即可完成BOM的重新勾选。"
                                }
                            ]
                        }
                    ],
                    "index": 1
                },
                {
                    "type": "image",
                    "bbox": [
                        83,
                        296,
                        508,
                        467
                    ],
                    "blocks": [
                        {
                            "bbox": [
                                83,
                                296,
                                508,
                                467
                            ],
                            "lines": [
                                {
                                    "bbox": [
                                        83,
                                        296,
                                        508,
                                        467
                                    ],
                                    "spans": [
                                        {
                                            "bbox": [
                                                83,
                                                296,
                                                508,
                                                467
                                            ],
                                            "type": "image",
                                            "image_path": "d63b8e0a44e5ae138567be50f6c00ca2d05442328ac19f2085ddfb4a5f0271ba.jpg"
                                        }
                                    ]
                                }
                            ],
                            "index": 2,
                            "angle": 0,
                            "type": "image_body"
                        }
                    ],
                    "index": 2
                },
                {
                    "bbox": [
                        81,
                        476,
                        511,
                        513
                    ],
                    "type": "text",
                    "angle": 0,
                    "lines": [
                        {
                            "bbox": [
                                81,
                                476,
                                511,
                                513
                            ],
                            "spans": [
                                {
                                    "bbox": [
                                        81,
                                        476,
                                        511,
                                        513
                                    ],
                                    "type": "text",
                                    "content": "步骤11：新品计划配套员依据“新品零部件需求BOM变更”申请，完成配套单贯改。"
                                }
                            ]
                        }
                    ],
                    "index": 3
                }
            ],
            "discarded_blocks": [
                {
                    "bbox": [
                        217,
                        796,
                        381,
                        808
                    ],
                    "type": "footer",
                    "angle": 0,
                    "lines": [
                        {
                            "bbox": [
                                217,
                                796,
                                381,
                                808
                            ],
                            "spans": [
                                {
                                    "bbox": [
                                        217,
                                        796,
                                        381,
                                        808
                                    ],
                                    "type": "text",
                                    "content": "陕西千山航空电子有限责任公司版权所有"
                                }
                            ]
                        }
                    ],
                    "index": 4
                },
                {
                    "bbox": [
                        447,
                        794,
                        511,
                        806
                    ],
                    "type": "page_number",
                    "angle": 0,
                    "lines": [
                        {
                            "bbox": [
                                447,
                                794,
                                511,
                                806
                            ],
                            "spans": [
                                {
                                    "bbox": [
                                        447,
                                        794,
                                        511,
                                        806
                                    ],
                                    "type": "text",
                                    "content": "共5页 第5页"
                                }
                            ]
                        }
                    ],
                    "index": 5
                }
            ],
            "page_size": [
                595,
                841
            ],
            "page_idx": 6
        }
    ],
    "_backend": "vlm",
    "_version_name": "2.5.3"
}